Metadata-Version: 2.1
Name: UUED
Version: 1.0.0
Summary: Unique ID Generator
Home-page: UNKNOWN
License: UNKNOWN
Platform: UNKNOWN
License-File: LICENSE
